hfortix/__init__.py
hfortix-0.5.148.dist-info/METADATA
hfortix-0.5.148.dist-info/WHEEL
hfortix-0.5.148.dist-info/top_level.txt
hfortix-0.5.148.dist-info/RECORD
