Metadata-Version: 2.4
Name: hfortix
Version: 0.5.148
Summary: Unified SDK for Fortinet products (FortiOS, FortiManager, FortiAnalyzer)
Author-email: "Herman W. Jacobsen" <herman@wjacobsen.fo>
License: Proprietary
Project-URL: Homepage, https://github.com/hermanwjacobsen/hfortix
Project-URL: Repository, https://github.com/hermanwjacobsen/hfortix
Keywords: fortinet,fortigate,fortios,fortimanager,fortianalyzer,api,sdk
Classifier: Development Status :: 4 - Beta
Classifier: Intended Audience :: Developers
Classifier: Programming Language :: Python :: 3
Classifier: Programming Language :: Python :: 3.10
Classifier: Programming Language :: Python :: 3.11
Classifier: Programming Language :: Python :: 3.12
Requires-Python: >=3.10
Requires-Dist: hfortix-core>=0.5.148
Requires-Dist: hfortix-fortios>=0.5.148
Provides-Extra: fortios
Requires-Dist: hfortix-fortios>=0.5.148; extra == "fortios"
Provides-Extra: all
Requires-Dist: hfortix-fortios>=0.5.148; extra == "all"
